rexpy.py
rexpy-0.0.0.dist-info/WHEEL
rexpy-0.0.0.dist-info/METADATA
rexpy-0.0.0.dist-info/RECORD
