Metadata-Version: 1.2
Name: rexpy
Version: 0.0.0
Summary: rexpy.py
Home-page: http://tdda.info/
License: UNKNOWN
Author: Stochastic Solutions Limited
Author-email: njr@StochasticSolutions.com
Classifier: License :: OSI Approved :: MIT License
